odoo10_addon_cms_info-10.0.1.0.0-py2.7-nspkg.pth
odoo/addons/cms_info/README.rst
odoo/addons/cms_info/__init__.py
odoo/addons/cms_info/__manifest__.py
odoo/addons/cms_info/models/__init__.py
odoo/addons/cms_info/models/website_mixin.py
odoo10_addon_cms_info-10.0.1.0.0.dist-info/DESCRIPTION.rst
odoo10_addon_cms_info-10.0.1.0.0.dist-info/METADATA
odoo10_addon_cms_info-10.0.1.0.0.dist-info/RECORD
odoo10_addon_cms_info-10.0.1.0.0.dist-info/WHEEL
odoo10_addon_cms_info-10.0.1.0.0.dist-info/metadata.json
odoo10_addon_cms_info-10.0.1.0.0.dist-info/namespace_packages.txt
odoo10_addon_cms_info-10.0.1.0.0.dist-info/top_level.txt
